argscall/__init__.py
argscall/argscaller.py
argscall/exceptions.py
argscall/version.py
tests/test_keyword_args.py
tests/test_positional_args.py
tests/test_some_arguments.py
tests/test_some_kwargs.py
tests/test_zero_arguments.py
argscall-0.0.2.dist-info/LICENSE
argscall-0.0.2.dist-info/METADATA
argscall-0.0.2.dist-info/WHEEL
argscall-0.0.2.dist-info/entry_points.txt
argscall-0.0.2.dist-info/top_level.txt
argscall-0.0.2.dist-info/RECORD
