Metadata-Version: 2.1
Name: argscall
Version: 0.0.2
Summary: functions while mapping and validating dynamic
Home-page: https://github.com/joaompinto/argscall
Author: João Pinto
Author-email: lamego.pinto@gmail.com
License: MIT
Platform: UNKNOWN
